{
  "Teacher": [],
  "Students": [],
  "Student": [],
  "1": [],
  "2": [],
  "Ali": [],
  "Erfan": [],
  "Nargess": [],
  "Tahereh": [],
  "Father": [],
  "Farid": [],
  "Mom": [],
  "Omid": [],
  "Hossein": [],
  "Ahmad": [],
  "Karimi": [],
  "Mohammadi": [],
  "Mehr": [],
  "Azadi": [],
  "Dad": [],
  "My": ["belonging to me", "من"],
  "name": ["what someone is called", "نام"],
  "Hi": ["greeting", "سلام"],
  "class": ["group of students", "کلاس"],
  "Hello": ["greeting", "سلام"],
  "Thank": ["express gratitude", "تشکر"],
  "you": ["person addressed", "تو"],
  "sit": ["rest on seat", "نشستن"],
  "down": ["lower position", "پایین"],
  "please": ["polite request", "لطفا"],
  "I": ["self", "من"],
  "am": ["exist", "هستم"],
  "your": ["belonging to you", "مال تو"],
  "English": ["language", "انگلیسی"],
  "teacher": ["educator", "معلم"],
  "is": ["to exist", "است"],
  "Now": ["current time", "اکنون"],
  "tell": ["communicate", "گفتن"],
  "me": ["object pronoun", "من"],
  "names": ["titles", "نام‌ها"],
  "What": ["question", "چه"],
  "How": ["in what way", "چگونه"],
  "are": ["plural be", "هستید"],
  "Fine": ["good condition", "خوب"],
  "And": ["addition", "و"],
  "who": ["which person", "کی"],
  "that": ["referring", "آن"],
  "boy": ["young male", "پسر"],
  "He": ["male pronoun", "او"],
  "our": ["belonging to us", "ما"],
  "new": ["recent", "جدید"],
  "classmate": ["school peer", "همکلاسی"],
  "Let": ["allow", "اجازه دادن"],
  "us": ["group including self", "ما"],
  "talk": ["speak", "صحبت"],
  "to": ["direction", "به"],
  "him": ["male object", "او"],
  "This": ["near thing", "این"],
  "Nice": ["pleasant", "خوشایند"],
  "meet": ["encounter", "ملاقات"],
  "too": ["also", "هم"],
  "Welcome": ["greeting", "خوش آمدید"],
  "school": ["education place", "مدرسه"],
  "when": ["at what time", "کی"],
  "birthday": ["birth date", "تولد"],
  "It": ["object pronoun", "آن"],
  "in": ["inside", "در"],
  "Really": ["truly", "واقعا"],
  "old": ["aged", "پیر"],
  "now": ["current moment", "اکنون"],
  "12": ["twelve", "دوازده"],
  "about": ["concerning", "درباره"],
  "picture": ["image", "تصویر"],
  "father": ["male parent", "پدر"],
  "Yes": ["affirmation", "بله"],
  "he": ["male pronoun", "او"],
  "38": ["thirty-eight", "سی و هشت"],
  "job": ["occupation", "شغل"],
  "a": ["article", "یک"],
  "mechanic": ["repair expert", "مکانیک"],
  "mother": ["female parent", "مادر"],
  "She": ["female pronoun", "او"],
  "35": ["thirty-five", "سی و پنج"],
  "housewife": ["homemaker", "خانه دار"],
  "appearance": ["looks", "ظاهر"],
  "No": ["negation", "نه"],
  "tall": ["height", "بلند"],
  "man": ["adult male", "مرد"],
  "wearing": ["having on", "پوشیدن"],
  "gray": ["color", "خاکستری"],
  "suit": ["formal clothes", "کت و شلوار"],
  "over": ["above", "روی"],
  "there": ["place", "آنجا"],
  "which": ["choice", "کدام"],
  "one": ["number", "یک"],
  "math": ["mathematics", "ریاضی"],
  "blue": ["color", "آبی"],
  "white": ["color", "سفید"],
  "shirt": ["clothing", "پیراهن"],
  "first": ["initial", "اول"],
  "house": ["home", "خانه"],
  "where": ["location", "کجا"],
  "kitchen": ["cooking room", "آشپزخانه"],
  "garage": ["car storage", "گاراژ"],
  "doing": ["performing", "انجام دادن"],
  "so": ["very", "خیلی"],
  "hungry": ["need food", "گرسنه"],
  "OK": ["approval", "خوب"],
  "wash": ["clean", "شستن"],
  "hands": ["body parts", "دست‌ها"],
  "come": ["approach", "آمدن"],
  "lunch": ["midday meal", "ناهار"],
  "call": ["contact", "تماس"],
  "fixing": ["repairing", "تعمیر"],
  "car": ["vehicle", "ماشین"],
  "address": ["location", "آدرس"],
  "not": ["negation", "نه"],
  "well": ["healthy", "خوب"],
  "today": ["this day", "امروز"],
  "time": ["clock measurement", "زمان"],
  "going": ["moving", "رفتن"],
  "visit": ["see someone", "ملاقات"],
  "Are": ["plural be", "هستید"],
  "coming": ["approaching", "آمدن"],
  "with": ["accompanying", "با"],
  "around": ["approximately", "حدود"],
  "5": ["five", "پنج"],
  "afternoon": ["time after noon", "عصر"],
  "sure": ["certain", "مطمئن"],
  "can": ["able to", "توانستن"],
  "but": ["however", "اما"],
  "try": ["attempt", "تلاش"],
  "Street": ["road", "خیابان"],
  "Call": ["contact", "تماس"],
  "before": ["prior", "قبل"],
  "go": ["move", "رفتن"],
  "phone": ["telephone", "تلفن"],
  "number": ["numeral", "شماره"],
  "586": ["five-eight-six", "پانصدوهشتادوشش"],
  "2144": ["two-one-four-four", "دوهزاروصدوچهل وچهار"],
  "bye": ["goodbye", "خداحافظ"],
  "Favorite": ["preferred", "محبوب"],
  "Food": ["nutrition", "غذا"],
  "Look": ["see", "نگاه کن"],
  "enough": ["sufficient", "کافی"],
  "have": ["possess", "داشتن"],
  "some": ["few", "چند"],
  "cake": ["dessert", "کیک"],
  "milk": ["dairy drink", "شیر"],
  "Sounds": ["seems", "به نظر میرسد"],
  "good": ["positive", "خوب"],
  "like": ["enjoy", "دوست داشتن"],
  "tea": ["beverage", "چای"],
  "favorite": ["preferred", "محبوب"],
  "Shayan": [],
  "Chaychi": [],
  "Sam": [],
  "Reihaneh": [],
  "Shiva": [],
  "Elham": [],
  "Sara": [],
  "Phanindra": [],
  "Morteza": [],
  "Hamid": [],
  "Zahra": [],
  "Samira": [],
  "Emami": [],
  "Iran": [],
  "France": [],
  "Isfahan": [],
  "Ghez-ghal’eh": [],
  "Azarbaijan": [],
  "Khoy": [],
  "Aban": [],
  "Farvardin": [],
  "Mr.": ["title for men", "آقای"],
  "cousin": ["family relative", "پسرعمو"],
  "speaks": ["talks", "صحبت میکند"],
  "French": ["language", "فرانسوی"],
  "little": ["small amount", "کم"],
  "Persian": ["language", "فارسی"],
  "Oh": ["expression", "اوه"],
  "originally": ["initially", "اصالتا"],
  "Iranian": ["from Iran", "ایرانی"],
  "live": ["reside", "زندگی کردن"],
  "country": ["nation", "کشور"],
  "week": ["7 days", "هفته"],
  "afternoons": ["time period", "عصرها"],
  "gym": ["exercise place", "باشگاه"],
  "Sundays": ["day", "یکشنبه‌ها"],
  "Tuesdays": ["day", "سه‌شنبه‌ها"],
  "Friday": ["day", "جمعه"],
  "mornings": ["early day", "صبح‌ها"],
  "stay": ["remain", "ماندن"],
  "relax": ["rest", "استراحت"],
  "know": ["be aware", "دانستن"],
  "help": ["assist", "کمک"],
  "sounds": ["seems", "به نظر میرسد"],
  "Wednesday": ["day", "چهارشنبه"],
  "let": ["allow", "اجازه دادن"],
  "abilities": ["skills", "توانایی‌ها"],
  "Wow": ["exclamation", "وای"],
  "drawing": ["art", "نقاشی"],
  "photos": ["pictures", "عکس‌ها"],
  "see": ["look", "دیدن"],
  "make": ["create", "ساختن"],
  "Thursday": ["day", "پنجشنبه"],
  "bring": ["carry", "آوردن"],
  "book": ["reading material", "کتاب"],
  "health": ["wellbeing", "سلامتی"],
  "headache": ["head pain", "سردرد"],
  "sore": ["painful", "دردناک"],
  "eyes": ["vision organs", "چشم‌ها"],
  "should": ["ought to", "باید"],
  "rest": ["relax", "استراحت"],
  "worry": ["feel anxious", "نگران"],
  "office": ["workplace", "دفتر"],
  "parents": ["mother/father", "والدین"],
  "quiet": ["silent", "ساکت"],
  "minute": ["60 seconds", "دقیقه"],
  "city": ["urban area", "شهر"],
  "center": ["middle", "مرکز"],
  "clean": ["not dirty", "تمیز"],
  "famous": ["well-known", "معروف"],
  "mosques": ["Islamic temples", "مساجد"],
  "palaces": ["royal homes", "کاخ‌ها"],
  "museums": ["exhibition spaces", "موزه‌ها"],
  "soon": ["near future", "به زودی"],
  "special": ["unique", "خاص"],
  "downtown": ["city center", "مرکز شهر"],
  "village": ["small town", "روستا"],
  "West": ["direction", "غرب"],
  "near": ["close", "نزدیک"],
  "mountain": ["large hill", "کوه"],
  "trees": ["plants", "درخت‌ها"],
  "flowers": ["blooms", "گل‌ها"],
  "sunflower": ["plant", "آفتابگردان"],
  "fields": ["open areas", "مزرعه‌ها"],
  "people": ["humans", "مردم"],
  "work": ["labor", "کار"],
  "farms": ["agricultural land", "مزرعه‌ها"],
  "raise": ["bring up", "پرورش دادن"],
  "animals": ["creatures", "حیوانات"],
  "weather": ["climate", "هوا"],
  "wind": ["air movement", "باد"],
  "summer": ["season", "تابستان"],
  "fall": ["autumn", "پاییز"],
  "winter": ["season", "زمستان"],
  "cold": ["low temperature", "سرد"],
  "interesting": ["fascinating", "جالب"],
  "hobbies": ["leisure activities", "سرگرمی‌ها"],
  "watch": ["view", "تماشا کردن"],
  "movies": ["films", "فیلم‌ها"],
  "reading": ["interpret text", "خواندن"],
  "sort": ["type", "نوع"],
  "magazines": ["periodicals", "مجله‌ها"],
  "sports": ["athletics", "ورزشی"],
  "news": ["information", "اخبار"],
  "Net": ["internet", "اینترنت"],
  "poems": ["verses", "اشعار"],
  "usually": ["normally", "معمولا"],
  "free": ["not occupied", "آزاد"],
  "Ehsan": [],
  "Parham": [],
  "Reza": [],
  "Paul": [],
  "Kress": [],
  "Germany": [],
  "Tehran": [],
  "Nasrin": [],
  "Nowruz": [],
  "Pedram": [],
  "Mina": [],
  "Mahsa": [],
  "Fajr": [],
  "Helal-e-Ahmar": [],
  "advice": ["guidance", "راهنمایی"],
  "after": ["following", "بعد"],
  "aid": ["help", "کمک"],
  "also": ["too", "همچنین"],
  "always": ["at all times", "همیشه"],
  "an": ["one", "یک"],
  "and": ["plus", "و"],
  "ankle": ["joint", "مچ"],
  "another": ["one more", "دیگر"],
  "any": ["some", "هر"],
  "attended": ["was present", "حاضر"],
  "back": ["rear", "پشت"],
  "bad": ["not good", "بد"],
  "be": ["exist", "بودن"],
  "because": ["since", "زیرا"],
  "best": ["most good", "بهترین"],
  "broke": ["fractured", "شکست"],
  "by": ["near", "کنار"],
  "care": ["attention", "مراقبت"],
  "ceremonies": ["events", "مراسم"],
  "check": ["verify", "بررسی"],
  "clever": ["smart", "باهوش"],
  "corner": ["angle", "گوشه"],
  "could": ["was able", "توانست"],
  "day": ["24 hours", "روز"],
  "did": ["completed", "انجام داد"],
  "different": ["not same", "متفاوت"],
  "don’t": ["do not", "نکن"],
  "each": ["every", "هر"],
  "early": ["before time", "زود"],
  "eat": ["consume food", "خوردن"],
  "envelope": ["paper cover", "پاکت"],
  "enjoy": ["have fun", "لذت"],
  "events": ["occasions", "رویدادها"],
  "excuse": ["pardon", "ببخشید"],
  "fell": ["dropped", "افتاد"],
  "festival": ["celebration", "جشن"],
  "film": ["movie", "فیلم"],
  "for": ["intended", "برای"],
  "friend": ["companion", "دوست"],
  "fun": ["enjoyment", "تفریح"],
  "gift": ["present", "هدیه"],
  "give": ["offer", "دادن"],
  "grandmother": ["mother's mother", "مادربزرگ"],
  "great": ["excellent", "عالی"],
  "happen": ["occur", "اتفاق"],
  "hard-working": ["diligent", "سخت‌کوش"],
  "has": ["owns", "دارد"],
  "her": ["female person", "او"],
  "here": ["this place", "اینجا"],
  "his": ["belonging to him", "او"],
  "holiday": ["vacation", "تعطیلات"],
  "hotel": ["inn", "هتل"],
  "how": ["in what way", "چگونه"],
  "if": ["in case", "اگر"],
  "important": ["significant", "مهم"],
  "injury": ["harm", "آسیب"],
  "international": ["global", "بین‌المللی"],
  "it": ["thing", "آن"],
  "its": ["belonging", "آن"],
  "just": ["only", "فقط"],
  "kind": ["nice", "مهربان"],
  "lake": ["large water", "دریاچه"],
  "last": ["final", "آخر"],
  "learned": ["gained knowledge", "یادگرفت"],
  "leg": ["limb", "پا"],
  "lesson": ["class", "درس"],
  "lot": ["much", "زیاد"],
  "love": ["strong liking", "عشق"],
  "mail": ["post", "پست"],
  "many": ["a lot", "زیاد"],
  "meal": ["food", "غذا"],
  "moment": ["short time", "لحظه"],
  "money": ["currency", "پول"],
  "more": ["extra", "بیشتر"],
  "most": ["greatest", "بیشترین"],
  "movie": ["film", "فیلم"],
  "much": ["a lot", "زیاد"],
  "my": ["belonging to me", "من"],
  "need": ["require", "نیاز"],
  "next": ["following", "بعدی"],
  "night": ["dark time", "شب"],
  "no": ["negative", "نه"],
  "of": ["belonging", "از"],
  "on": ["upon", "روی"],
  "open": ["unlocked", "باز"],
  "or": ["alternative", "یا"],
  "out": ["outside", "بیرون"],
  "passport": ["travel document", "گذرنامه"],
  "plan": ["arrange", "برنامه"],
  "postcard": ["small card", "کارت پستال"],
  "really": ["truly", "واقعا"],
  "she": ["female person", "او"],
  "shop": ["store", "فروشگاه"],
  "sick": ["ill", "بیمار"],
  "sometimes": ["occasionally", "گاهی"],
  "stamp": ["postal mark", "تمبر"],
  "take": ["grab", "گرفتن"],
  "thanks": ["gratitude", "تشکر"],
  "thing": ["object", "چیز"],
  "this": ["nearby", "این"],
  "tourist": ["traveler", "گردشگر"],
  "use": ["apply", "استفاده"],
  "very": ["extremely", "خیلی"],
  "want": ["desire", "خواستن"],
  "was": ["past of is", "بود"],
  "what": ["question", "چی"],
  "yes": ["positive", "بله"],
  "Personality": ["character traits", "شخصیت"],
  "helpful": ["assisting", "کمک کننده"],
  "lessons": ["classes", "درس‌ها"],
  "Travel": ["journey", "سفر"],
  "sir": ["formal address", "آقا"],
  "reservation": ["booking", "رزرو"],
  "staying": ["remaining", "ماندن"],
  "nights": ["evenings", "شب‌ها"],
  "wife": ["spouse", "همسر"],
  "visiting": ["traveling to", "بازدید"],
  "standing": ["on feet", "ایستاده"],
  "key": ["opener", "کلید"],
  "room": ["chamber", "اتاق"],
  "213": ["two-thirteen", "دویست وسیزده"],
  "Festivals": ["celebrations", "جشنواره‌ها"],
  "Ceremonies": ["rituals", "مراسم"],
  "holidays": ["time off", "تعطیلات"],
  "relatives": ["family members", "فامیل"],
  "gifts": ["presents", "هدایا"],
  "grandparents": ["elders", "پدربزرگ مادربزرگ"],
  "houses": ["homes", "خانه‌ها"],
  "cook": ["prepare food", "پختن"],
  "Services": ["assistance", "خدمات"],
  "post": ["mail service", "پست"],
  "round": ["circular", "دور"],
  "Media": ["communication", "رسانه"],
  "weekend": ["days off", "آخر هفته"],
  "International": ["global", "بین المللی"],
  "Film": ["movie", "فیلم"],
  "interested": ["curious", "علاقه مند"],
  "reports": ["accounts", "گزارشات"],
  "TV": ["television", "تلویزیون"],
  "read": ["peruse", "خواندن"],
  "surf": ["browse", "گشتن"],
  "website": ["online site", "وب سایت"],
  "texted": ["messaged", "پیام داد"],
  "Health": ["wellbeing", "سلامتی"],
  "Injuries": ["wounds", "آسیب‌ها"],
  "trips": ["journeys", "سفرها"],
  "twisted": ["sprained", "پیچ خورد"],
  "participated": ["joined", "شرکت کرد"],
  "classes": ["courses", "کلاس‌ها"]
}
